{
  "markers": [
    {
      "Map": "Valguero_P.ark",
      "Category": "",
      "Name": "Cave (Spider)",
      "Image": "",
      "Colour": -8323073,
      "BorderColour": -65536,
      "BorderWidth": 1,
      "Lat": 73.0,
      "Lon": 40.0,
      "Visible": false
    },
    {
      "Map": "Valguero_P.ark",
      "Category": "",
      "Name": "Cave (Temple)",
      "Image": "",
      "Colour": -8323073,
      "BorderColour": -65536,
      "BorderWidth": 1,
      "Lat": 44.0,
      "Lon": 84.0,
      "Visible": false
    },
    {
      "Map": "Valguero_P.ark",
      "Category": "",
      "Name": "Cave (Aberration)",
      "Image": "",
      "Colour": -8323073,
      "BorderColour": -65408,
      "BorderWidth": 1,
      "Lat": 38.0,
      "Lon": 57.0,
      "Visible": false
    },
    {
      "Map": "Valguero_P.ark",
      "Category": "",
      "Name": "Cave (Ice)",
      "Image": "",
      "Colour": -1,
      "BorderColour": -65536,
      "BorderWidth": 1,
      "Lat": 15.0,
      "Lon": 27.0,
      "Visible": false
    },
    {
      "Map": "Valguero_P.ark",
      "Category": "",
      "Name": "Cave (Aberration)",
      "Image": "",
      "Colour": -8323073,
      "BorderColour": -8388353,
      "BorderWidth": 1,
      "Lat": 32.0,
      "Lon": 92.0,
      "Visible": false
    },
    {
      "Map": "Valguero_P.ark",
      "Category": "",
      "Name": "Cave (Water)",
      "Image": "",
      "Colour": -8323073,
      "BorderColour": -65536,
      "BorderWidth": 1,
      "Lat": 45.0,
      "Lon": 34.0,
      "Visible": false
    },
    {
      "Map": "Valguero_P.ark",
      "Category": "",
      "Name": "Cave (Water)",
      "Image": "",
      "Colour": -8323073,
      "BorderColour": -65536,
      "BorderWidth": 1,
      "Lat": 32.0,
      "Lon": 9.0,
      "Visible": false
    },
    {
      "Map": "Valguero_P.ark",
      "Category": "",
      "Name": "Cave (Water)",
      "Image": "",
      "Colour": -8323073,
      "BorderColour": -65536,
      "BorderWidth": 1,
      "Lat": 63.5,
      "Lon": 73.0,
      "Visible": false
    },
    {
      "Map": "theisland.ark",
      "Category": "",
      "Name": "Cave (Central)",
      "Image": "001-cave.png",
      "Colour": -1,
      "BorderColour": -65536,
      "BorderWidth": 1,
      "Lat": 41.5,
      "Lon": 46.9,
      "Visible": true
    },
    {
      "Map": "theisland.ark",
      "Category": "",
      "Name": "Cave (Lower South)",
      "Image": "001-cave.png",
      "Colour": -1,
      "BorderColour": -65536,
      "BorderWidth": 1,
      "Lat": 80.3,
      "Lon": 53.5,
      "Visible": true
    },
    {
      "Map": "theisland.ark",
      "Category": "",
      "Name": "Cave (North East)",
      "Image": "001-cave.png",
      "Colour": -1,
      "BorderColour": -65536,
      "BorderWidth": 1,
      "Lat": 14.7,
      "Lon": 85.4,
      "Visible": true
    },
    {
      "Map": "theisland.ark",
      "Category": "",
      "Name": "Cave (Upper South)",
      "Image": "001-cave.png",
      "Colour": -1,
      "BorderColour": -65536,
      "BorderWidth": 1,
      "Lat": 68.2,
      "Lon": 56.2,
      "Visible": true
    },
    {
      "Map": "theisland.ark",
      "Category": "",
      "Name": "Cave (South East)",
      "Image": "001-cave.png",
      "Colour": -1,
      "BorderColour": -65536,
      "BorderWidth": 1,
      "Lat": 70.6,
      "Lon": 86.1,
      "Visible": true
    },
    {
      "Map": "theisland.ark",
      "Category": "",
      "Name": "Cave (Swamp)",
      "Image": "001-cave.png",
      "Colour": -1,
      "BorderColour": -65536,
      "BorderWidth": 1,
      "Lat": 62.7,
      "Lon": 37.3,
      "Visible": true
    },
    {
      "Map": "theisland.ark",
      "Category": "",
      "Name": "Cave (Lost Faith)",
      "Image": "001-cave.png",
      "Colour": -1,
      "BorderColour": -65536,
      "BorderWidth": 1,
      "Lat": 53.7,
      "Lon": 10.4,
      "Visible": true
    },
    {
      "Map": "theisland.ark",
      "Category": "",
      "Name": "Cave  (Lost Hope)",
      "Image": "001-cave.png",
      "Colour": -1,
      "BorderColour": -65536,
      "BorderWidth": 1,
      "Lat": 45.9,
      "Lon": 88.9,
      "Visible": true
    },
    {
      "Map": "theisland.ark",
      "Category": "",
      "Name": "Cave (Tek)",
      "Image": "011-cave-1.png",
      "Colour": -1,
      "BorderColour": -65536,
      "BorderWidth": 1,
      "Lat": 43.1,
      "Lon": 39.1,
      "Visible": true
    },
    {
      "Map": "theisland.ark",
      "Category": "",
      "Name": "Cave (Snow)",
      "Image": "002-north-pole.png",
      "Colour": -1,
      "BorderColour": -65536,
      "BorderWidth": 1,
      "Lat": 29.1,
      "Lon": 31.8,
      "Visible": true
    },
    {
      "Map": "theisland.ark",
      "Category": "",
      "Name": "Cave (North West)",
      "Image": "001-cave.png",
      "Colour": -1,
      "BorderColour": -65536,
      "BorderWidth": 1,
      "Lat": 19.3,
      "Lon": 19.0,
      "Visible": true
    },
    {
      "Map": "Extinction.ark",
      "Category": "",
      "Name": "Cave (Desert)",
      "Image": "011-cave-1.png",
      "Colour": -1,
      "BorderColour": -65536,
      "BorderWidth": 1,
      "Lat": 87.4,
      "Lon": 70.4,
      "Visible": true
    },
    {
      "Map": "Extinction.ark",
      "Category": "",
      "Name": "Cave (Ice)",
      "Image": "002-north-pole.png",
      "Colour": -1,
      "BorderColour": -65536,
      "BorderWidth": 1,
      "Lat": 20.3,
      "Lon": 62.2,
      "Visible": true
    },
    {
      "Map": "Extinction.ark",
      "Category": "",
      "Name": "Underground Forest Cave",
      "Image": "011-cave-1.png",
      "Colour": -1,
      "BorderColour": -65536,
      "BorderWidth": 1,
      "Lat": 11.8,
      "Lon": 39.3,
      "Visible": true
    },
    {
      "Map": "ragnarok.ark",
      "Category": "",
      "Name": "Loot 1",
      "Image": "027-treasure.png",
      "Colour": -128,
      "BorderColour": -16777216,
      "BorderWidth": 0,
      "Lat": 84.1,
      "Lon": 77.0,
      "Visible": false
    },
    {
      "Map": "ragnarok.ark",
      "Category": "",
      "Name": "Loot 2",
      "Image": "027-treasure.png",
      "Colour": -256,
      "BorderColour": -16777216,
      "BorderWidth": 0,
      "Lat": 70.0,
      "Lon": 76.5,
      "Visible": false
    },
    {
      "Map": "ragnarok.ark",
      "Category": "",
      "Name": "Loot 5",
      "Image": "027-treasure.png",
      "Colour": -256,
      "BorderColour": -16777216,
      "BorderWidth": 0,
      "Lat": 79.7,
      "Lon": 51.9,
      "Visible": false
    },
    {
      "Map": "ragnarok.ark",
      "Category": "",
      "Name": "Loot 4",
      "Image": "027-treasure.png",
      "Colour": -256,
      "BorderColour": -16777216,
      "BorderWidth": 0,
      "Lat": 59.7,
      "Lon": 76.5,
      "Visible": false
    },
    {
      "Map": "ragnarok.ark",
      "Category": "",
      "Name": "Loot 3",
      "Image": "027-treasure.png",
      "Colour": -256,
      "BorderColour": -16777216,
      "BorderWidth": 0,
      "Lat": 63.2,
      "Lon": 78.1,
      "Visible": false
    },
    {
      "Map": "Ragnarok",
      "Category": "",
      "Name": "The Monkeys Puzzle",
      "Image": "011-cave-1.png",
      "Colour": -1,
      "BorderColour": -65536,
      "BorderWidth": 1,
      "Lat": 24.6,
      "Lon": 25.0,
      "Visible": true
    },
    {
      "Map": "Ragnarok",
      "Category": "",
      "Name": "Lifes Labyrinth",
      "Image": "011-cave-1.png",
      "Colour": -1,
      "BorderColour": -65536,
      "BorderWidth": 1,
      "Lat": 51.6,
      "Lon": 77.5,
      "Visible": true
    },
    {
      "Map": "TheCenter.ark",
      "Category": "",
      "Name": "Water Dome",
      "Image": "011-cave-1.png",
      "Colour": -1,
      "BorderColour": -65536,
      "BorderWidth": 1,
      "Lat": 23.0,
      "Lon": 88.0,
      "Visible": true
    },
    {
      "Map": "TheCenter.ark",
      "Category": "",
      "Name": "East Lava Cave",
      "Image": "011-cave-1.png",
      "Colour": -1,
      "BorderColour": -65536,
      "BorderWidth": 1,
      "Lat": 11.2,
      "Lon": 67.4,
      "Visible": true
    },
    {
      "Map": "TheCenter.ark",
      "Category": "",
      "Name": "West Lava Cave",
      "Image": "011-cave-1.png",
      "Colour": -1,
      "BorderColour": -65536,
      "BorderWidth": 1,
      "Lat": 15.8,
      "Lon": 50.5,
      "Visible": true
    },
    {
      "Map": "TheCenter.ark",
      "Category": "",
      "Name": "North Ice Cave",
      "Image": "002-north-pole.png",
      "Colour": -1,
      "BorderColour": -65536,
      "BorderWidth": 1,
      "Lat": 18.7,
      "Lon": 29.7,
      "Visible": true
    },
    {
      "Map": "TheCenter.ark",
      "Category": "",
      "Name": "South Ice Cave",
      "Image": "002-north-pole.png",
      "Colour": -1,
      "BorderColour": -65536,
      "BorderWidth": 1,
      "Lat": 54.0,
      "Lon": 20.9,
      "Visible": true
    },
    {
      "Map": "TheCenter.ark",
      "Category": "",
      "Name": "Cliffside Cavern - 3",
      "Image": "011-cave-1.png",
      "Colour": -1,
      "BorderColour": -65536,
      "BorderWidth": 1,
      "Lat": 36.0,
      "Lon": 2.0,
      "Visible": true
    },
    {
      "Map": "TheCenter.ark",
      "Category": "",
      "Name": "Cliffside Cavern - 2",
      "Image": "011-cave-1.png",
      "Colour": -1,
      "BorderColour": -65536,
      "BorderWidth": 1,
      "Lat": 21.0,
      "Lon": 13.5,
      "Visible": true
    },
    {
      "Map": "TheCenter.ark",
      "Category": "",
      "Name": "Cliffside Cavern - 1",
      "Image": "011-cave-1.png",
      "Colour": -1,
      "BorderColour": -65536,
      "BorderWidth": 1,
      "Lat": 58.1,
      "Lon": 12.8,
      "Visible": true
    },
    {
      "Map": "TheCenter.ark",
      "Category": "",
      "Name": "The Central Cave - 3",
      "Image": "011-cave-1.png",
      "Colour": -1,
      "BorderColour": -65536,
      "BorderWidth": 1,
      "Lat": 40.3,
      "Lon": 31.1,
      "Visible": true
    },
    {
      "Map": "TheCenter.ark",
      "Category": "",
      "Name": "The Central Cave - 2",
      "Image": "011-cave-1.png",
      "Colour": -1,
      "BorderColour": -65536,
      "BorderWidth": 1,
      "Lat": 36.4,
      "Lon": 35.0,
      "Visible": true
    },
    {
      "Map": "TheCenter.ark",
      "Category": "",
      "Name": "The Central Cave - 1",
      "Image": "011-cave-1.png",
      "Colour": -1,
      "BorderColour": -65536,
      "BorderWidth": 1,
      "Lat": 35.9,
      "Lon": 34.4,
      "Visible": true
    },
    {
      "Map": "TheCenter.ark",
      "Category": "",
      "Name": "Underground World - 6",
      "Image": "011-cave-1.png",
      "Colour": -1,
      "BorderColour": -65536,
      "BorderWidth": 1,
      "Lat": 66.1,
      "Lon": 51.7,
      "Visible": true
    },
    {
      "Map": "TheCenter.ark",
      "Category": "",
      "Name": "Underground World - 5",
      "Image": "011-cave-1.png",
      "Colour": -1,
      "BorderColour": -65536,
      "BorderWidth": 1,
      "Lat": 44.2,
      "Lon": 58.0,
      "Visible": true
    },
    {
      "Map": "TheCenter.ark",
      "Category": "",
      "Name": "Underground World - 4",
      "Image": "011-cave-1.png",
      "Colour": -1,
      "BorderColour": -65536,
      "BorderWidth": 1,
      "Lat": 32.7,
      "Lon": 64.1,
      "Visible": true
    },
    {
      "Map": "TheCenter.ark",
      "Category": "",
      "Name": "Underground World - 3",
      "Image": "011-cave-1.png",
      "Colour": -1,
      "BorderColour": -65536,
      "BorderWidth": 1,
      "Lat": 53.5,
      "Lon": 53.8,
      "Visible": true
    },
    {
      "Map": "TheCenter.ark",
      "Category": "",
      "Name": "Underground World - 2",
      "Image": "011-cave-1.png",
      "Colour": -1,
      "BorderColour": -65536,
      "BorderWidth": 1,
      "Lat": 34.3,
      "Lon": 53.3,
      "Visible": true
    },
    {
      "Map": "TheCenter.ark",
      "Category": "",
      "Name": "Underground World - 1",
      "Image": "011-cave-1.png",
      "Colour": -1,
      "BorderColour": -65536,
      "BorderWidth": 1,
      "Lat": 34.9,
      "Lon": 65.8,
      "Visible": true
    },
    {
      "Map": "TheCenter.ark",
      "Category": "",
      "Name": "Jungle Cave - 5",
      "Image": "011-cave-1.png",
      "Colour": -1,
      "BorderColour": -65536,
      "BorderWidth": 1,
      "Lat": 46.3,
      "Lon": 63.1,
      "Visible": true
    },
    {
      "Map": "TheCenter.ark",
      "Category": "",
      "Name": "Jungle Cave - 4",
      "Image": "011-cave-1.png",
      "Colour": -1,
      "BorderColour": -65536,
      "BorderWidth": 1,
      "Lat": 50.8,
      "Lon": 71.3,
      "Visible": true
    },
    {
      "Map": "TheCenter.ark",
      "Category": "",
      "Name": "Jungle Cave - 3",
      "Image": "011-cave-1.png",
      "Colour": -1,
      "BorderColour": -65536,
      "BorderWidth": 1,
      "Lat": 45.0,
      "Lon": 64.0,
      "Visible": true
    },
    {
      "Map": "TheCenter.ark",
      "Category": "",
      "Name": "Jungle Cave - 2",
      "Image": "011-cave-1.png",
      "Colour": -1,
      "BorderColour": -65536,
      "BorderWidth": 1,
      "Lat": 52.5,
      "Lon": 67.7,
      "Visible": true
    },
    {
      "Map": "TheCenter.ark",
      "Category": "",
      "Name": "Jungle Cave - 1",
      "Image": "011-cave-1.png",
      "Colour": -1,
      "BorderColour": -65536,
      "BorderWidth": 1,
      "Lat": 54.2,
      "Lon": 62.7,
      "Visible": true
    },
    {
      "Map": "Hope",
      "Category": "",
      "Name": "Small Cave",
      "Image": "011-cave-1.png",
      "Colour": -1,
      "BorderColour": -65536,
      "BorderWidth": 1,
      "Lat": 55.7,
      "Lon": 17.8,
      "Visible": true
    },
    {
      "Map": "Hope",
      "Category": "",
      "Name": "Ab Cave",
      "Image": "001-cave.png",
      "Colour": -1,
      "BorderColour": -65536,
      "BorderWidth": 1,
      "Lat": 55.5,
      "Lon": 50.8,
      "Visible": true
    },
    {
      "Map": "Hope",
      "Category": "",
      "Name": "Small Cave 2",
      "Image": "011-cave-1.png",
      "Colour": -1,
      "BorderColour": -65536,
      "BorderWidth": 1,
      "Lat": 38.5,
      "Lon": 57.8,
      "Visible": true
    },
    {
      "Map": "Hope",
      "Category": "",
      "Name": "Water Cave",
      "Image": "011-cave-1.png",
      "Colour": -1,
      "BorderColour": -65536,
      "BorderWidth": 1,
      "Lat": 47.6,
      "Lon": 96.7,
      "Visible": true
    },
    {
      "Map": "ScorchedEarth_P.ark",
      "Category": "",
      "Name": "Cave (The Old Tunnels)",
      "Image": "011-cave-1.png",
      "Colour": -1,
      "BorderColour": -65536,
      "BorderWidth": 1,
      "Lat": 58.7,
      "Lon": 47.9,
      "Visible": true
    },
    {
      "Map": "ScorchedEarth_P.ark",
      "Category": "",
      "Name": "Cave (The Tyrant)",
      "Image": "011-cave-1.png",
      "Colour": -1,
      "BorderColour": -65536,
      "BorderWidth": 1,
      "Lat": 28.5,
      "Lon": 29.3,
      "Visible": true
    },
    {
      "Map": "ScorchedEarth_P.ark",
      "Category": "",
      "Name": "Cave (Ruins of Nosti)",
      "Image": "011-cave-1.png",
      "Colour": -1,
      "BorderColour": -65536,
      "BorderWidth": 1,
      "Lat": 77.8,
      "Lon": 75.6,
      "Visible": true
    },
    {
      "Map": "CrystalIsles",
      "Category": "",
      "Name": "Bee Cave",
      "Image": "005-bee.png",
      "Colour": -1,
      "BorderColour": -256,
      "BorderWidth": 1,
      "Lat": 39.0,
      "Lon": 19.3,
      "Visible": true
    },
    {
      "Map": "CrystalIsles",
      "Category": "",
      "Name": "Ice Cave",
      "Image": "002-north-pole.png",
      "Colour": -1,
      "BorderColour": -65536,
      "BorderWidth": 1,
      "Lat": 31.5,
      "Lon": 50.7,
      "Visible": true
    },
    {
      "Map": "CrystalIsles",
      "Category": "",
      "Name": "Ice Cave 2",
      "Image": "011-cave-1.png",
      "Colour": -1,
      "BorderColour": -65536,
      "BorderWidth": 1,
      "Lat": 33.0,
      "Lon": 49.4,
      "Visible": false
    },
    {
      "Map": "CrystalIsles",
      "Category": "",
      "Name": "Ice Cave 3",
      "Image": "002-north-pole.png",
      "Colour": -1,
      "BorderColour": -65536,
      "BorderWidth": 1,
      "Lat": 34.0,
      "Lon": 49.8,
      "Visible": false
    },
    {
      "Map": "CrystalIsles",
      "Category": "",
      "Name": "Ice Cave 4",
      "Image": "002-north-pole.png",
      "Colour": -1,
      "BorderColour": -65536,
      "BorderWidth": 1,
      "Lat": 37.7,
      "Lon": 49.5,
      "Visible": false
    },
    {
      "Map": "CrystalIsles",
      "Category": "",
      "Name": "Sky Cave 1",
      "Image": "011-cave-1.png",
      "Colour": -1,
      "BorderColour": -65536,
      "BorderWidth": 1,
      "Lat": 44.6,
      "Lon": 75.2,
      "Visible": true
    },
    {
      "Map": "CrystalIsles",
      "Category": "",
      "Name": "Sky Cave 2",
      "Image": "011-cave-1.png",
      "Colour": -1,
      "BorderColour": -65536,
      "BorderWidth": 1,
      "Lat": 45.1,
      "Lon": 78.4,
      "Visible": false
    },
    {
      "Map": "CrystalIsles",
      "Category": "",
      "Name": "Sky Cave 3",
      "Image": "011-cave-1.png",
      "Colour": -1,
      "BorderColour": -65536,
      "BorderWidth": 1,
      "Lat": 47.3,
      "Lon": 76.9,
      "Visible": false
    },
    {
      "Map": "CrystalIsles",
      "Category": "",
      "Name": "Dragon Temple",
      "Image": "011-cave-1.png",
      "Colour": -1,
      "BorderColour": -65536,
      "BorderWidth": 1,
      "Lat": 48.4,
      "Lon": 75.2,
      "Visible": true
    },
    {
      "Map": "Aberration_P.ark",
      "Category": "",
      "Name": "Cave (Elemental Vault)",
      "Image": "011-cave-1.png",
      "Colour": -1,
      "BorderColour": -65536,
      "BorderWidth": 1,
      "Lat": 81.0,
      "Lon": 47.7,
      "Visible": false
    },
    {
      "Map": "Aberration_P.ark",
      "Category": "",
      "Name": "Cave (Old Railway)",
      "Image": "011-cave-1.png",
      "Colour": -1,
      "BorderColour": -65536,
      "BorderWidth": 1,
      "Lat": 42.8,
      "Lon": 27.1,
      "Visible": false
    },
    {
      "Map": "Aberration_P.ark",
      "Category": "",
      "Name": "Cave (Hiden Grotto)",
      "Image": "011-cave-1.png",
      "Colour": -1,
      "BorderColour": -65536,
      "BorderWidth": 1,
      "Lat": 55.3,
      "Lon": 65.9,
      "Visible": false
    },
    {
      "Map": "Aberration_P.ark",
      "Category": "",
      "Name": "Surface (Green Obelisk 2)",
      "Image": "011-cave-1.png",
      "Colour": -1,
      "BorderColour": -8323073,
      "BorderWidth": 1,
      "Lat": 34.6,
      "Lon": 82.1,
      "Visible": false
    },
    {
      "Map": "Aberration_P.ark",
      "Category": "",
      "Name": "Cave (Blue Obelisk)",
      "Image": "011-cave-1.png",
      "Colour": -1,
      "BorderColour": -8323073,
      "BorderWidth": 1,
      "Lat": 19.5,
      "Lon": 27.2,
      "Visible": false
    },
    {
      "Map": "Aberration_P.ark",
      "Category": "",
      "Name": "Surface (Blue Obelisk)",
      "Image": "011-cave-1.png",
      "Colour": -1,
      "BorderColour": -8323073,
      "BorderWidth": 1,
      "Lat": 17.2,
      "Lon": 23.5,
      "Visible": false
    },
    {
      "Map": "Aberration_P.ark",
      "Category": "",
      "Name": "Cave (Green Obelisk)",
      "Image": "011-cave-1.png",
      "Colour": -1,
      "BorderColour": -8323073,
      "BorderWidth": 1,
      "Lat": 26.8,
      "Lon": 63.2,
      "Visible": false
    },
    {
      "Map": "Aberration_P.ark",
      "Category": "",
      "Name": "Surface (Green Obelisk)",
      "Image": "011-cave-1.png",
      "Colour": -1,
      "BorderColour": -8323073,
      "BorderWidth": 1,
      "Lat": 24.9,
      "Lon": 65.1,
      "Visible": false
    },
    {
      "Map": "Aberration_P.ark",
      "Category": "",
      "Name": "Cave (Green Obelisk 2)",
      "Image": "011-cave-1.png",
      "Colour": -1,
      "BorderColour": -8323073,
      "BorderWidth": 1,
      "Lat": 37.1,
      "Lon": 80.3,
      "Visible": false
    },
    {
      "Map": "Aberration_P.ark",
      "Category": "",
      "Name": "Cave (Red Obelisk)",
      "Image": "011-cave-1.png",
      "Colour": -1,
      "BorderColour": -8323073,
      "BorderWidth": 1,
      "Lat": 52.3,
      "Lon": 23.3,
      "Visible": false
    },
    {
      "Map": "Aberration_P.ark",
      "Category": "",
      "Name": "Surface (Red Obelisk)",
      "Image": "011-cave-1.png",
      "Colour": -1,
      "BorderColour": -8323073,
      "BorderWidth": 1,
      "Lat": 56.1,
      "Lon": 23.7,
      "Visible": false
    },
    {
      "Map": "Aberration_P.ark",
      "Category": "",
      "Name": "Cave (Red Obelisk 2)",
      "Image": "011-cave-1.png",
      "Colour": -1,
      "BorderColour": -8323073,
      "BorderWidth": 1,
      "Lat": 79.2,
      "Lon": 27.8,
      "Visible": false
    },
    {
      "Map": "Aberration_P.ark",
      "Category": "",
      "Name": "Surface (Red Obelisk 2)",
      "Image": "011-cave-1.png",
      "Colour": -1,
      "BorderColour": -8323073,
      "BorderWidth": 1,
      "Lat": 79.8,
      "Lon": 24.5,
      "Visible": false
    },
    {
      "Map": "Genesis",
      "Category": "",
      "Name": "Cave",
      "Image": "013-eruption.png",
      "Colour": -1,
      "BorderColour": -65536,
      "BorderWidth": 1,
      "Lat": 33.2,
      "Lon": 82.5,
      "Visible": true
    },
    {
      "Map": "Genesis",
      "Category": "",
      "Name": "TEKnological Terrors",
      "Image": "005-seo-and-web.png",
      "Colour": -1,
      "BorderColour": -16777216,
      "BorderWidth": 1,
      "Lat": 14.2,
      "Lon": 29.7,
      "Visible": false
    },
    {
      "Map": "Genesis",
      "Category": "",
      "Name": "This little light of mine",
      "Image": "005-seo-and-web.png",
      "Colour": -1,
      "BorderColour": -16777216,
      "BorderWidth": 1,
      "Lat": 21.1,
      "Lon": 27.9,
      "Visible": false
    },
    {
      "Map": "Genesis",
      "Category": "",
      "Name": "Dont fear the Reaper King",
      "Image": "005-seo-and-web.png",
      "Colour": -1,
      "BorderColour": -16777216,
      "BorderWidth": 1,
      "Lat": 27.8,
      "Lon": 16.9,
      "Visible": false
    },
    {
      "Map": "Genesis",
      "Category": "",
      "Name": "To Boldly Go",
      "Image": "005-seo-and-web.png",
      "Colour": -1,
      "BorderColour": -16777216,
      "BorderWidth": 1,
      "Lat": 35.0,
      "Lon": 28.2,
      "Visible": false
    },
    {
      "Map": "Genesis",
      "Category": "",
      "Name": "Hunting by moonlight",
      "Image": "005-seo-and-web.png",
      "Colour": -1,
      "BorderColour": -16777216,
      "BorderWidth": 1,
      "Lat": 43.9,
      "Lon": 25.4,
      "Visible": false
    },
    {
      "Map": "Genesis",
      "Category": "",
      "Name": "Tokyo Skift",
      "Image": "005-seo-and-web.png",
      "Colour": -1,
      "BorderColour": -16777216,
      "BorderWidth": 1,
      "Lat": 48.4,
      "Lon": 27.7,
      "Visible": false
    },
    {
      "Map": "Genesis",
      "Category": "",
      "Name": "Space Jam",
      "Image": "005-seo-and-web.png",
      "Colour": -1,
      "BorderColour": -16777216,
      "BorderWidth": 1,
      "Lat": 50.3,
      "Lon": 28.1,
      "Visible": false
    },
    {
      "Map": "Genesis",
      "Category": "",
      "Name": "A captains conquest",
      "Image": "005-seo-and-web.png",
      "Colour": -1,
      "BorderColour": -16777216,
      "BorderWidth": 1,
      "Lat": 49.3,
      "Lon": 30.6,
      "Visible": false
    },
    {
      "Map": "Genesis",
      "Category": "",
      "Name": "Echo of a Classic",
      "Image": "005-seo-and-web.png",
      "Colour": -1,
      "BorderColour": -16777216,
      "BorderWidth": 1,
      "Lat": 20.2,
      "Lon": 61.6,
      "Visible": false
    },
    {
      "Map": "Genesis",
      "Category": "",
      "Name": "Chasing the White Whale",
      "Image": "005-seo-and-web.png",
      "Colour": -1,
      "BorderColour": -16777216,
      "BorderWidth": 1,
      "Lat": 26.5,
      "Lon": 51.8,
      "Visible": false
    },
    {
      "Map": "Genesis",
      "Category": "",
      "Name": "The Teeth Underneath",
      "Image": "005-seo-and-web.png",
      "Colour": -1,
      "BorderColour": -16777216,
      "BorderWidth": 1,
      "Lat": 28.7,
      "Lon": 52.5,
      "Visible": false
    },
    {
      "Map": "Genesis",
      "Category": "",
      "Name": "Wave Ray 64",
      "Image": "005-seo-and-web.png",
      "Colour": -1,
      "BorderColour": -16777216,
      "BorderWidth": 1,
      "Lat": 30.4,
      "Lon": 49.7,
      "Visible": false
    },
    {
      "Map": "Genesis",
      "Category": "",
      "Name": "Who hid the squid?",
      "Image": "005-seo-and-web.png",
      "Colour": -1,
      "BorderColour": -16777216,
      "BorderWidth": 1,
      "Lat": 30.2,
      "Lon": 55.8,
      "Visible": false
    },
    {
      "Map": "Genesis",
      "Category": "",
      "Name": "Hide and Sink",
      "Image": "005-seo-and-web.png",
      "Colour": -1,
      "BorderColour": -16777216,
      "BorderWidth": 1,
      "Lat": 30.9,
      "Lon": 55.9,
      "Visible": false
    },
    {
      "Map": "Genesis",
      "Category": "",
      "Name": "Rip It",
      "Image": "005-seo-and-web.png",
      "Colour": -1,
      "BorderColour": -16777216,
      "BorderWidth": 1,
      "Lat": 31.6,
      "Lon": 57.5,
      "Visible": false
    },
    {
      "Map": "Genesis",
      "Category": "",
      "Name": "Bottle-nosed Blitz",
      "Image": "005-seo-and-web.png",
      "Colour": -1,
      "BorderColour": -16777216,
      "BorderWidth": 1,
      "Lat": 34.3,
      "Lon": 51.6,
      "Visible": false
    },
    {
      "Map": "Genesis",
      "Category": "",
      "Name": "One Tough Moeder",
      "Image": "005-seo-and-web.png",
      "Colour": -1,
      "BorderColour": -16777216,
      "BorderWidth": 1,
      "Lat": 39.5,
      "Lon": 52.1,
      "Visible": false
    },
    {
      "Map": "Genesis",
      "Category": "",
      "Name": "Out of the Frying Pan",
      "Image": "005-seo-and-web.png",
      "Colour": -1,
      "BorderColour": -16777216,
      "BorderWidth": 1,
      "Lat": 15.1,
      "Lon": 70.6,
      "Visible": false
    },
    {
      "Map": "Genesis",
      "Category": "",
      "Name": "The Egg-straction",
      "Image": "005-seo-and-web.png",
      "Colour": -1,
      "BorderColour": -16777216,
      "BorderWidth": 1,
      "Lat": 32.5,
      "Lon": 86.0,
      "Visible": false
    },
    {
      "Map": "Genesis",
      "Category": "",
      "Name": "Gotta Go Fast",
      "Image": "005-seo-and-web.png",
      "Colour": -1,
      "BorderColour": -16777216,
      "BorderWidth": 1,
      "Lat": 33.7,
      "Lon": 85.2,
      "Visible": false
    },
    {
      "Map": "Genesis",
      "Category": "",
      "Name": "We Will Rock You",
      "Image": "005-seo-and-web.png",
      "Colour": -1,
      "BorderColour": -16777216,
      "BorderWidth": 1,
      "Lat": 33.3,
      "Lon": 85.9,
      "Visible": false
    },
    {
      "Map": "Genesis",
      "Category": "",
      "Name": "The Summit Tour",
      "Image": "005-seo-and-web.png",
      "Colour": -1,
      "BorderColour": -16777216,
      "BorderWidth": 1,
      "Lat": 32.8,
      "Lon": 88.1,
      "Visible": false
    },
    {
      "Map": "Genesis",
      "Category": "",
      "Name": "One Hell of a Treasure Hunt",
      "Image": "005-seo-and-web.png",
      "Colour": -1,
      "BorderColour": -16777216,
      "BorderWidth": 1,
      "Lat": 40.7,
      "Lon": 81.8,
      "Visible": false
    },
    {
      "Map": "Genesis",
      "Category": "",
      "Name": "Dead Heat",
      "Image": "005-seo-and-web.png",
      "Colour": -1,
      "BorderColour": -16777216,
      "BorderWidth": 1,
      "Lat": 41.8,
      "Lon": 82.2,
      "Visible": false
    },
    {
      "Map": "Genesis",
      "Category": "",
      "Name": "Allo and Goodbye",
      "Image": "005-seo-and-web.png",
      "Colour": -1,
      "BorderColour": -16777216,
      "BorderWidth": 1,
      "Lat": 41.3,
      "Lon": 86.7,
      "Visible": false
    },
    {
      "Map": "Genesis",
      "Category": "",
      "Name": "Magma Medley Melee",
      "Image": "005-seo-and-web.png",
      "Colour": -1,
      "BorderColour": -16777216,
      "BorderWidth": 1,
      "Lat": 45.1,
      "Lon": 80.8,
      "Visible": false
    },
    {
      "Map": "Genesis",
      "Category": "",
      "Name": "Dodoball Pick-Up",
      "Image": "005-seo-and-web.png",
      "Colour": -1,
      "BorderColour": -16777216,
      "BorderWidth": 1,
      "Lat": 54.2,
      "Lon": 84.7,
      "Visible": false
    },
    {
      "Map": "Genesis",
      "Category": "",
      "Name": "Bog Rally",
      "Image": "005-seo-and-web.png",
      "Colour": -1,
      "BorderColour": -16777216,
      "BorderWidth": 1,
      "Lat": 60.1,
      "Lon": 84.1,
      "Visible": false
    },
    {
      "Map": "Genesis",
      "Category": "",
      "Name": "Cheaper by the Pack",
      "Image": "005-seo-and-web.png",
      "Colour": -1,
      "BorderColour": -16777216,
      "BorderWidth": 1,
      "Lat": 62.7,
      "Lon": 87.4,
      "Visible": false
    },
    {
      "Map": "Genesis",
      "Category": "",
      "Name": "Another Bog Hunt",
      "Image": "005-seo-and-web.png",
      "Colour": -1,
      "BorderColour": -16777216,
      "BorderWidth": 1,
      "Lat": 68.3,
      "Lon": 86.3,
      "Visible": false
    },
    {
      "Map": "Genesis",
      "Category": "",
      "Name": "Along Came Pollen",
      "Image": "005-seo-and-web.png",
      "Colour": -1,
      "BorderColour": -16777216,
      "BorderWidth": 1,
      "Lat": 75.0,
      "Lon": 68.0,
      "Visible": false
    },
    {
      "Map": "Genesis",
      "Category": "",
      "Name": "Spy vs Spino",
      "Image": "005-seo-and-web.png",
      "Colour": -1,
      "BorderColour": -16777216,
      "BorderWidth": 1,
      "Lat": 84.8,
      "Lon": 57.4,
      "Visible": false
    },
    {
      "Map": "Genesis",
      "Category": "",
      "Name": "Bog Beatdown",
      "Image": "005-seo-and-web.png",
      "Colour": -1,
      "BorderColour": -16777216,
      "BorderWidth": 1,
      "Lat": 84.9,
      "Lon": 61.1,
      "Visible": false
    },
    {
      "Map": "Genesis",
      "Category": "",
      "Name": "Mission",
      "Image": "005-seo-and-web.png",
      "Colour": -1,
      "BorderColour": -16777216,
      "BorderWidth": 1,
      "Lat": 84.1,
      "Lon": 69.9,
      "Visible": false
    },
    {
      "Map": "Genesis",
      "Category": "",
      "Name": "Bog Fishin",
      "Image": "005-seo-and-web.png",
      "Colour": -1,
      "BorderColour": -16777216,
      "BorderWidth": 1,
      "Lat": 85.3,
      "Lon": 71.6,
      "Visible": false
    },
    {
      "Map": "Genesis",
      "Category": "",
      "Name": "Just a Hop",
      "Image": "005-seo-and-web.png",
      "Colour": -1,
      "BorderColour": -16777216,
      "BorderWidth": 1,
      "Lat": 86.8,
      "Lon": 73.5,
      "Visible": false
    },
    {
      "Map": "Genesis",
      "Category": "",
      "Name": "Home is where the pouch is",
      "Image": "005-seo-and-web.png",
      "Colour": -1,
      "BorderColour": -16777216,
      "BorderWidth": 1,
      "Lat": 62.0,
      "Lon": 26.8,
      "Visible": false
    },
    {
      "Map": "Genesis",
      "Category": "",
      "Name": "The Rhino 500",
      "Image": "005-seo-and-web.png",
      "Colour": -1,
      "BorderColour": -16777216,
      "BorderWidth": 1,
      "Lat": 61.1,
      "Lon": 33.1,
      "Visible": false
    },
    {
      "Map": "Genesis",
      "Category": "",
      "Name": "Searching the Fro-zone",
      "Image": "005-seo-and-web.png",
      "Colour": -1,
      "BorderColour": -16777216,
      "BorderWidth": 1,
      "Lat": 61.7,
      "Lon": 34.7,
      "Visible": false
    },
    {
      "Map": "Genesis",
      "Category": "",
      "Name": "Ruffle Some Feathers",
      "Image": "005-seo-and-web.png",
      "Colour": -1,
      "BorderColour": -16777216,
      "BorderWidth": 1,
      "Lat": 63.9,
      "Lon": 41.3,
      "Visible": false
    },
    {
      "Map": "Genesis",
      "Category": "",
      "Name": "Built Fjord Tough",
      "Image": "005-seo-and-web.png",
      "Colour": -1,
      "BorderColour": -16777216,
      "BorderWidth": 1,
      "Lat": 63.5,
      "Lon": 49.8,
      "Visible": false
    },
    {
      "Map": "Genesis",
      "Category": "",
      "Name": "Ice Fishin",
      "Image": "005-seo-and-web.png",
      "Colour": -1,
      "BorderColour": -16777216,
      "BorderWidth": 1,
      "Lat": 69.0,
      "Lon": 21.3,
      "Visible": false
    },
    {
      "Map": "Genesis",
      "Category": "",
      "Name": "Mound oOver Matter",
      "Image": "005-seo-and-web.png",
      "Colour": -1,
      "BorderColour": -16777216,
      "BorderWidth": 1,
      "Lat": 70.7,
      "Lon": 26.2,
      "Visible": false
    },
    {
      "Map": "Genesis",
      "Category": "",
      "Name": "Saber Slalom",
      "Image": "005-seo-and-web.png",
      "Colour": -1,
      "BorderColour": -16777216,
      "BorderWidth": 1,
      "Lat": 70.6,
      "Lon": 33.1,
      "Visible": false
    },
    {
      "Map": "Genesis",
      "Category": "",
      "Name": "Hyde and Seek",
      "Image": "005-seo-and-web.png",
      "Colour": -1,
      "BorderColour": -16777216,
      "BorderWidth": 1,
      "Lat": 76.0,
      "Lon": 45.1,
      "Visible": false
    },
    {
      "Map": "Gen2",
      "Category": "",
      "Name": "Despatcher 1",
      "Image": "005-seo-and-web.png",
      "Colour": -1,
      "BorderColour": -16777216,
      "BorderWidth": 1,
      "Lat": 19.3,
      "Lon": 31.9,
      "Visible": false
    },
    {
      "Map": "Gen2",
      "Category": "",
      "Name": "Despatcher 10",
      "Image": "005-seo-and-web.png",
      "Colour": -1,
      "BorderColour": -16777216,
      "BorderWidth": 1,
      "Lat": 56.4,
      "Lon": 36.6,
      "Visible": false
    },
    {
      "Map": "Gen2",
      "Category": "",
      "Name": "Despatcher 11",
      "Image": "005-seo-and-web.png",
      "Colour": -1,
      "BorderColour": -16777216,
      "BorderWidth": 1,
      "Lat": 72.9,
      "Lon": 22.6,
      "Visible": false
    },
    {
      "Map": "Gen2",
      "Category": "",
      "Name": "Despatcher 12",
      "Image": "005-seo-and-web.png",
      "Colour": -1,
      "BorderColour": -16777216,
      "BorderWidth": 1,
      "Lat": 74.3,
      "Lon": 32.4,
      "Visible": false
    },
    {
      "Map": "Gen2",
      "Category": "",
      "Name": "Despatcher 13",
      "Image": "005-seo-and-web.png",
      "Colour": -1,
      "BorderColour": -16777216,
      "BorderWidth": 1,
      "Lat": 80.7,
      "Lon": 7.5,
      "Visible": false
    },
    {
      "Map": "Gen2",
      "Category": "",
      "Name": "Despatcher 14",
      "Image": "005-seo-and-web.png",
      "Colour": -1,
      "BorderColour": -16777216,
      "BorderWidth": 1,
      "Lat": 18.8,
      "Lon": 89.5,
      "Visible": false
    },
    {
      "Map": "Gen2",
      "Category": "",
      "Name": "Despatcher 15",
      "Image": "005-seo-and-web.png",
      "Colour": -1,
      "BorderColour": -16777216,
      "BorderWidth": 1,
      "Lat": 23.8,
      "Lon": 61.6,
      "Visible": false
    },
    {
      "Map": "Gen2",
      "Category": "",
      "Name": "Despatcher 16",
      "Image": "005-seo-and-web.png",
      "Colour": -1,
      "BorderColour": -16777216,
      "BorderWidth": 1,
      "Lat": 33.7,
      "Lon": 79.1,
      "Visible": false
    },
    {
      "Map": "Gen2",
      "Category": "",
      "Name": "Despatcher 17",
      "Image": "005-seo-and-web.png",
      "Colour": -1,
      "BorderColour": -16777216,
      "BorderWidth": 1,
      "Lat": 32.9,
      "Lon": 90.7,
      "Visible": false
    },
    {
      "Map": "Gen2",
      "Category": "",
      "Name": "Despatcher 18",
      "Image": "005-seo-and-web.png",
      "Colour": -1,
      "BorderColour": -16777216,
      "BorderWidth": 1,
      "Lat": 38.2,
      "Lon": 66.2,
      "Visible": false
    },
    {
      "Map": "Gen2",
      "Category": "",
      "Name": "Despatcher 19",
      "Image": "005-seo-and-web.png",
      "Colour": -1,
      "BorderColour": -16777216,
      "BorderWidth": 1,
      "Lat": 38.4,
      "Lon": 83.8,
      "Visible": false
    },
    {
      "Map": "Gen2",
      "Category": "",
      "Name": "Despatcher 2",
      "Image": "005-seo-and-web.png",
      "Colour": -1,
      "BorderColour": -16777216,
      "BorderWidth": 1,
      "Lat": 24.4,
      "Lon": 27.6,
      "Visible": false
    },
    {
      "Map": "Gen2",
      "Category": "",
      "Name": "Despatcher 20",
      "Image": "005-seo-and-web.png",
      "Colour": -1,
      "BorderColour": -16777216,
      "BorderWidth": 1,
      "Lat": 41.1,
      "Lon": 60.5,
      "Visible": false
    },
    {
      "Map": "Gen2",
      "Category": "",
      "Name": "Despatcher 21",
      "Image": "005-seo-and-web.png",
      "Colour": -1,
      "BorderColour": -16777216,
      "BorderWidth": 1,
      "Lat": 40.8,
      "Lon": 76.8,
      "Visible": false
    },
    {
      "Map": "Gen2",
      "Category": "",
      "Name": "Despatcher 22",
      "Image": "005-seo-and-web.png",
      "Colour": -1,
      "BorderColour": -16777216,
      "BorderWidth": 1,
      "Lat": 41.8,
      "Lon": 80.9,
      "Visible": false
    },
    {
      "Map": "Gen2",
      "Category": "",
      "Name": "Despatcher 23",
      "Image": "005-seo-and-web.png",
      "Colour": -1,
      "BorderColour": -16777216,
      "BorderWidth": 1,
      "Lat": 55.4,
      "Lon": 76.7,
      "Visible": false
    },
    {
      "Map": "Gen2",
      "Category": "",
      "Name": "Despatcher 24",
      "Image": "005-seo-and-web.png",
      "Colour": -1,
      "BorderColour": -16777216,
      "BorderWidth": 1,
      "Lat": 57.5,
      "Lon": 69.3,
      "Visible": false
    },
    {
      "Map": "Gen2",
      "Category": "",
      "Name": "Despatcher 25",
      "Image": "005-seo-and-web.png",
      "Colour": -1,
      "BorderColour": -16777216,
      "BorderWidth": 1,
      "Lat": 56.8,
      "Lon": 90.8,
      "Visible": false
    },
    {
      "Map": "Gen2",
      "Category": "",
      "Name": "Despatcher 26",
      "Image": "005-seo-and-web.png",
      "Colour": -1,
      "BorderColour": -16777216,
      "BorderWidth": 1,
      "Lat": 63.0,
      "Lon": 63.8,
      "Visible": false
    },
    {
      "Map": "Gen2",
      "Category": "",
      "Name": "Despatcher 27",
      "Image": "005-seo-and-web.png",
      "Colour": -1,
      "BorderColour": -16777216,
      "BorderWidth": 1,
      "Lat": 69.9,
      "Lon": 60.1,
      "Visible": false
    },
    {
      "Map": "Gen2",
      "Category": "",
      "Name": "Despatcher 28",
      "Image": "005-seo-and-web.png",
      "Colour": -1,
      "BorderColour": -16777216,
      "BorderWidth": 1,
      "Lat": 79.5,
      "Lon": 90.2,
      "Visible": false
    },
    {
      "Map": "Gen2",
      "Category": "",
      "Name": "Despatcher 3",
      "Image": "005-seo-and-web.png",
      "Colour": -1,
      "BorderColour": -16777216,
      "BorderWidth": 1,
      "Lat": 26.4,
      "Lon": 9.3,
      "Visible": false
    },
    {
      "Map": "Gen2",
      "Category": "",
      "Name": "Despatcher 4",
      "Image": "005-seo-and-web.png",
      "Colour": -1,
      "BorderColour": -16777216,
      "BorderWidth": 1,
      "Lat": 40.5,
      "Lon": 9.8,
      "Visible": false
    },
    {
      "Map": "Gen2",
      "Category": "",
      "Name": "Despatcher 5",
      "Image": "005-seo-and-web.png",
      "Colour": -1,
      "BorderColour": -16777216,
      "BorderWidth": 1,
      "Lat": 40.1,
      "Lon": 30.2,
      "Visible": false
    },
    {
      "Map": "Gen2",
      "Category": "",
      "Name": "Despatcher 6",
      "Image": "005-seo-and-web.png",
      "Colour": -1,
      "BorderColour": -16777216,
      "BorderWidth": 1,
      "Lat": 42.1,
      "Lon": 24.7,
      "Visible": false
    },
    {
      "Map": "Gen2",
      "Category": "",
      "Name": "Despatcher 7",
      "Image": "005-seo-and-web.png",
      "Colour": -1,
      "BorderColour": -16777216,
      "BorderWidth": 1,
      "Lat": 42.4,
      "Lon": 37.1,
      "Visible": false
    },
    {
      "Map": "Gen2",
      "Category": "",
      "Name": "Despatcher 8",
      "Image": "005-seo-and-web.png",
      "Colour": -1,
      "BorderColour": -16777216,
      "BorderWidth": 1,
      "Lat": 56.2,
      "Lon": 15.4,
      "Visible": false
    },
    {
      "Map": "Gen2",
      "Category": "",
      "Name": "Despatcher 9",
      "Image": "005-seo-and-web.png",
      "Colour": -1,
      "BorderColour": -16777216,
      "BorderWidth": 1,
      "Lat": 56.5,
      "Lon": 24.4,
      "Visible": false
    }
  ]
}